CHANGES.txt
CONTRIBUTORS.txt
MANIFEST.in
README.txt
setup.py
collective/__init__.py
collective.portlet.googleapps.egg-info/PKG-INFO
collective.portlet.googleapps.egg-info/SOURCES.txt
collective.portlet.googleapps.egg-info/dependency_links.txt
collective.portlet.googleapps.egg-info/entry_points.txt
collective.portlet.googleapps.egg-info/namespace_packages.txt
collective.portlet.googleapps.egg-info/not-zip-safe
collective.portlet.googleapps.egg-info/paster_plugins.txt
collective.portlet.googleapps.egg-info/requires.txt
collective.portlet.googleapps.egg-info/top_level.txt
collective/portlet/__init__.py
collective/portlet/googleapps/README.txt
collective/portlet/googleapps/__init__.py
collective/portlet/googleapps/config.py
collective/portlet/googleapps/configure.zcml
collective/portlet/googleapps/interfaces.py
collective/portlet/googleapps/skins.zcml
collective/portlet/googleapps/tests.py
collective/portlet/googleapps/browser/__init__.py
collective/portlet/googleapps/browser/configure.zcml
collective/portlet/googleapps/browser/interfaces.py
collective/portlet/googleapps/browser/images/README.txt
collective/portlet/googleapps/browser/javascripts/README.txt
collective/portlet/googleapps/browser/javascripts/collective_portlet_googleapps.js
collective/portlet/googleapps/browser/stylesheets/README.txt
collective/portlet/googleapps/browser/stylesheets/collective_portlet_googleapps.css
collective/portlet/googleapps/browser/templates/README.txt
collective/portlet/googleapps/content/__init__.py
collective/portlet/googleapps/content/configure.zcml
collective/portlet/googleapps/portlets/__init__.py
collective/portlet/googleapps/portlets/__init__.py~
collective/portlet/googleapps/portlets/configure.zcml
collective/portlet/googleapps/portlets/configure.zcml~
collective/portlet/googleapps/portlets/googleauthenticationportlet.pt~
collective/portlet/googleapps/portlets/googleauthenticationportlet.py~
collective/portlet/googleapps/portlets/googlecalendarportlet.pt
collective/portlet/googleapps/portlets/googlecalendarportlet.pt~
collective/portlet/googleapps/portlets/googlecalendarportlet.py
collective/portlet/googleapps/portlets/googlecalendarportlet.py~
collective/portlet/googleapps/portlets/googledocsportlet.pt
collective/portlet/googleapps/portlets/googledocsportlet.pt~
collective/portlet/googleapps/portlets/googledocsportlet.py
collective/portlet/googleapps/portlets/googledocsportlet.py~
collective/portlet/googleapps/portlets/googlemailportlet.pt
