Metadata-Version: 1.0
Name: collective.portlet.googleapps
Version: 0.1
Summary: A collection of portlets to provide connectivity to Google Apps
Home-page: http://eresearch.jcu.edu.au
Author: David Breitkreutz
Author-email: david.breitkreutz@jcu.edu.au
License: GPL
Keywords: plone portlet docs google
Platform: UNKNOWN
Classifier: Framework :: Plone
Classifier: Intended Audience :: Developers
Classifier: Topic :: Software Development :: Libraries :: Python Modules
Classifier: License :: OSI Approved :: GNU General Public License (GPL)
